package/__init__.py
package/modul1.py
package/modul2.py
demo_project_et123-0.0.1.dist-info/METADATA
demo_project_et123-0.0.1.dist-info/WHEEL
demo_project_et123-0.0.1.dist-info/top_level.txt
demo_project_et123-0.0.1.dist-info/RECORD
