Metadata-Version: 2.1
Name: demo_project_et123
Version: 0.0.1
Summary: Demonstration PyPI Upload
Author-email: Thomas Benkenstein <thomas.benkenstein@experteach.de>
Classifier: Programming Language :: Python :: 3.12
Classifier: Development Status :: 2 - Pre-Alpha
Classifier: Operating System :: Microsoft :: Windows :: Windows 11
Requires-Python: >=3.10
Requires-Dist: numpy>=2.0.0
Requires-Dist: pandas
